freshdata/__init__.py
freshdata/model_card_client.py
fresh_data-0.0.3.dist-info/LICENSE
fresh_data-0.0.3.dist-info/METADATA
fresh_data-0.0.3.dist-info/WHEEL
fresh_data-0.0.3.dist-info/top_level.txt
fresh_data-0.0.3.dist-info/RECORD
