Metadata-Version: 2.1
Name: fresh-data
Version: 0.0.3
Summary: Data Science for Humans!
Author: Fresh Data LLC.
Author-email: getfreshdata@gmail.com
Classifier: Programming Language :: Python :: 3
Classifier: License :: OSI Approved :: MIT License
Classifier: Operating System :: OS Independent
Requires-Python: >=3.6
License-File: LICENSE
